bcsfe/__init__.py
bcsfe/__main__.py
bcsfe/py.typed
bcsfe/cli/__init__.py
bcsfe/cli/color.py
bcsfe/cli/dialog_creator.py
bcsfe/cli/feature_handler.py
bcsfe/cli/file_dialog.py
bcsfe/cli/main.py
bcsfe/cli/save_management.py
bcsfe/cli/server_cli.py
bcsfe/cli/edits/__init__.py
bcsfe/cli/edits/aku_realm.py
bcsfe/cli/edits/basic_items.py
bcsfe/cli/edits/cat_editor.py
bcsfe/cli/edits/clear_tutorial.py
bcsfe/cli/edits/enemy_editor.py
bcsfe/cli/edits/event_tickets.py
bcsfe/cli/edits/fixes.py
bcsfe/cli/edits/map.py
bcsfe/cli/edits/max_all.py
bcsfe/cli/edits/rare_ticket_trade.py
bcsfe/cli/edits/storage.py
bcsfe/core/__init__.py
bcsfe/core/country_code.py
bcsfe/core/crypto.py
bcsfe/core/game_version.py
bcsfe/core/locale_handler.py
bcsfe/core/log.py
bcsfe/core/max_value_helper.py
bcsfe/core/theme_handler.py
bcsfe/core/game/__init__.py
bcsfe/core/game/localizable.py
bcsfe/core/game/battle/__init__.py
bcsfe/core/game/battle/battle_items.py
bcsfe/core/game/battle/cleared_slots.py
bcsfe/core/game/battle/enemy.py
bcsfe/core/game/battle/slots.py
bcsfe/core/game/catbase/__init__.py
bcsfe/core/game/catbase/beacon_base.py
bcsfe/core/game/catbase/cat.py
bcsfe/core/game/catbase/drop_chara.py
bcsfe/core/game/catbase/gambling.py
bcsfe/core/game/catbase/gatya.py
bcsfe/core/game/catbase/gatya_item.py
bcsfe/core/game/catbase/item_pack.py
bcsfe/core/game/catbase/login_bonuses.py
bcsfe/core/game/catbase/matatabi.py
bcsfe/core/game/catbase/medals.py
bcsfe/core/game/catbase/mission.py
bcsfe/core/game/catbase/my_sale.py
bcsfe/core/game/catbase/nyanko_club.py
bcsfe/core/game/catbase/officer_pass.py
bcsfe/core/game/catbase/playtime.py
bcsfe/core/game/catbase/powerup.py
bcsfe/core/game/catbase/scheme_items.py
bcsfe/core/game/catbase/special_skill.py
bcsfe/core/game/catbase/stamp.py
bcsfe/core/game/catbase/talent_orbs.py
bcsfe/core/game/catbase/unlock_popups.py
bcsfe/core/game/catbase/upgrade.py
bcsfe/core/game/catbase/user_rank_rewards.py
bcsfe/core/game/gamoto/__init__.py
bcsfe-3.2.2.dist-info/licenses/LICENSE
bcsfe-3.2.2.dist-info/METADATA
bcsfe-3.2.2.dist-info/WHEEL
bcsfe-3.2.2.dist-info/entry_points.txt
bcsfe-3.2.2.dist-info/top_level.txt
bcsfe-3.2.2.dist-info/RECORD
