Metadata-Version: 2.4
Name: bcsfe
Version: 3.2.2
Summary: A save file editor for The Battle Cats
Author: fieryhenry
License-Expression: GPL-3.0-or-later
Project-URL: Homepage, https://codeberg.org/fieryhenry/BCSFE-Python
Project-URL: Repository, https://codeberg.org/fieryhenry/BCSFE-Python
Project-URL: Issues, https://codeberg.org/fieryhenry/BCSFE-Python/issues
Project-URL: Changelog, https://codeberg.org/fieryhenry/BCSFE-Python/raw/branch/main/CHANGELOG.md
Keywords: battle cats,save editor,hacking
Classifier: Development Status :: 4 - Beta
Classifier: Intended Audience :: End Users/Desktop
Classifier: Topic :: Utilities
Classifier: Programming Language :: Python :: 3
Classifier: Programming Language :: Python :: 3.9
Classifier: Operating System :: OS Independent
Requires-Python: >=3.9
License-File: LICENSE
Requires-Dist: aenum
Requires-Dist: colored==1.4.4
Requires-Dist: pyjwt
Requires-Dist: requests
Requires-Dist: pyyaml
Requires-Dist: beautifulsoup4
Requires-Dist: argparse
Dynamic: license-file
